freq_del/freq_del.v
module freq_del
#(
    parameter EVEN_DIV = 6,
    parameter IMP_WAIT = 5
)
(
    input  wire     clk,
    input  wire   reset,
    
    output wire clk_div,
    output wire     imp
);
    
    localparam  COUNTER_SIZE = $clog2(EVEN_DIV);
    localparam COUNT_BOARDER = EVEN_DIV / 2 - 1;
    
    output reg [COUNTER_SIZE - 1: 0] counter;

    // freq division
    assign clk_div = (counter > COUNT_BOARDER);
    always @(posedge clk)
        if (reset)
            counter <= 0;
        else
            counter <= (counter == EVEN_DIV - 1) ? 'h0 : counter + 'h1;


/////////////////////////////////////////////////////////////////////////////////////

/////////////////////////////////////////////////////////////////////////////////////


    reg [2: 0] counter2;

    // impulse every IMP_WAIT cycles
    assign imp = (counter2 == IMP_WAIT - 1);
    always @(posedge clk)
        if (reset)
            counter2 <= 0;
        else
            counter2 <= (counter2 == IMP_WAIT - 1) ? 'h0 : counter2 + 'h1;

endmodule

freq_del/freq_test.v
`timescale 1ns/100ps

module freq_test
#(
    parameter EVEN_DIV = 14,
    parameter IMP_WAIT = 8
);

    reg   clk;
    reg reset;

    freq_del   
        #(.EVEN_DIV(EVEN_DIV), 
          .IMP_WAIT(IMP_WAIT))
    freq_del 
        (      .clk(clk     ),
             .reset(reset   )
        );

    always 
        #1 clk = ~clk;

    initial begin
        clk   <= 0;
        reset <= 1;
    end

    initial begin
		$dumpfile("dump.vcd"); $dumpvars(0, freq_test);
        #5; 
        reset = 0;
        #130;
        $finish;
    end

endmodule

freq_del/dump.vcd
$date
	Thu Oct 10 17:47:12 2024
$end
$version
	Icarus Verilog
$end
$timescale
	100ps
$end
$scope module freq_test $end
$var reg 1 ! clk $end
$var reg 1 " reset $end
$scope module freq_del $end
$var wire 1 ! clk $end
$var wire 1 " reset $end
$var wire 1 # imp $end
$var wire 1 $ clk_div $end
$var reg 4 % counter [3:0] $end
$var reg 3 & counter2 [2:0] $end
$upscope $end
$upscope $end
$enddefinitions $end
#0
$dumpvars
bx &
bx %
x$
x#
1"
0!
$end
#10
0$
b0 %
0#
b0 &
1!
#20
0!
#30
1!
#40
0!
#50
b1 %
b1 &
1!
0"
#60
0!
#70
b10 &
b10 %
1!
#80
0!
#90
b11 %
b11 &
1!
#100
0!
#110
b100 &
b100 %
1!
#120
0!
#130
b101 %
b101 &
1!
#140
0!
#150
b110 &
b110 %
1!
#160
0!
#170
1$
b111 %
1#
b111 &
1!
#180
0!
#190
0#
b0 &
b1000 %
1!
#200
0!
#210
b1001 %
b1 &
1!
#220
0!
#230
b10 &
b1010 %
1!
#240
0!
#250
b1011 %
b11 &
1!
#260
0!
#270
b100 &
b1100 %
1!
#280
0!
#290
b1101 %
b101 &
1!
#300
0!
#310
b110 &
0$
b0 %
1!
#320
0!
#330
b1 %
1#
b111 &
1!
#340
0!
#350
0#
b0 &
b10 %
1!
#360
0!
#370
b11 %
b1 &
1!
#380
0!
#390
b10 &
b100 %
1!
#400
0!
#410
b101 %
b11 &
1!
#420
0!
#430
b100 &
b110 %
1!
#440
0!
#450
1$
b111 %
b101 &
1!
#460
0!
#470
b110 &
b1000 %
1!
#480
0!
#490
b1001 %
1#
b111 &
1!
#500
0!
#510
0#
b0 &
b1010 %
1!
#520
0!
#530
b1011 %
b1 &
1!
#540
0!
#550
b10 &
b1100 %
1!
#560
0!
#570
b1101 %
b11 &
1!
#580
0!
#590
b100 &
0$
b0 %
1!
#600
0!
#610
b1 %
b101 &
1!
#620
0!
#630
b110 &
b10 %
1!
#640
0!
#650
b11 %
1#
b111 &
1!
#660
0!
#670
0#
b0 &
b100 %
1!
#680
0!
#690
b101 %
b1 &
1!
#700
0!
#710
b10 &
b110 %
1!
#720
0!
#730
1$
b111 %
b11 &
1!
#740
0!
#750
b100 &
b1000 %
1!
#760
0!
#770
b1001 %
b101 &
1!
#780
0!
#790
b110 &
b1010 %
1!
#800
0!
#810
b1011 %
1#
b111 &
1!
#820
0!
#830
0#
b0 &
b1100 %
1!
#840
0!
#850
b1101 %
b1 &
1!
#860
0!
#870
b10 &
0$
b0 %
1!
#880
0!
#890
b1 %
b11 &
1!
#900
0!
#910
b100 &
b10 %
1!
#920
0!
#930
b11 %
b101 &
1!
#940
0!
#950
b110 &
b100 %
1!
#960
0!
#970
b101 %
1#
b111 &
1!
#980
0!
#990
0#
b0 &
b110 %
1!
#1000
0!
#1010
1$
b111 %
b1 &
1!
#1020
0!
#1030
b10 &
b1000 %
1!
#1040
0!
#1050
b1001 %
b11 &
1!
#1060
0!
#1070
b100 &
b1010 %
1!
#1080
0!
#1090
b1011 %
b101 &
1!
#1100
0!
#1110
b110 &
b1100 %
1!
#1120
0!
#1130
b1101 %
1#
b111 &
1!
#1140
0!
#1150
0#
b0 &
0$
b0 %
1!
#1160
0!
#1170
b1 %
b1 &
1!
#1180
0!
#1190
b10 &
b10 %
1!
#1200
0!
#1210
b11 %
b11 &
1!
#1220
0!
#1230
b100 &
b100 %
1!
#1240
0!
#1250
b101 %
b101 &
1!
#1260
0!
#1270
b110 &
b110 %
1!
#1280
0!
#1290
1$
b111 %
1#
b111 &
1!
#1300
0!
#1310
0#
b0 &
b1000 %
1!
#1320
0!
#1330
b1001 %
b1 &
1!
#1340
0!
#1350
b10 &
b1010 %
1!
