freq_del/freq_del.v
module freq_del
(
    input clk,
    input reset
);
    
    reg [2: 0]  counter;
    reg [2: 0] counter2;
    wire           imp5;
    wire           clk6;

    assign clk6 = (counter   > 3'h2);
    assign imp5 = (counter2 == 3'h4);
   
    always @(posedge clk)
        counter  <= ~reset ? ((counter  == 3'h5) ?  3'h0 : counter  + 3'h1) : {2'h0, ~reset};

    always @(posedge clk)
        counter2 <= ~reset ? ((counter2 == 3'h4) ?  3'h0 : counter2 + 3'h1) : {2'h0, ~reset};

endmodule

freq_del/freq_test.v
`timescale 1ns/100ps

module freq_test;

reg   clk;
reg reset;

freq_del   freq_test 
        (  .clk(clk  ),
         .reset(reset)
        );

    always 
        #1 clk = ~clk;

    initial begin
        clk   <= 0;
        reset <= 1;
    end

    initial begin
		$dumpfile("dump.vcd"); $dumpvars(0, freq_test);
        #5; 
        reset = 0;
        #130;
        $finish;
    end

endmodule

freq_del/dump.vcd
$date
	Tue Sep 24 10:50:25 2024
$end
$version
	Icarus Verilog
$end
$timescale
	100ps
$end
$scope module freq_test $end
$scope module freq_test $end
$var wire 1 ! clk $end
$var wire 1 " reset $end
$var wire 1 # imp5 $end
$var wire 1 $ clk6 $end
$var reg 3 % counter [2:0] $end
$var reg 3 & counter2 [2:0] $end
$upscope $end
$upscope $end
$enddefinitions $end
#0
$dumpvars
bx &
bx %
x$
x#
1"
0!
$end
#10
0$
b0 %
0#
b0 &
1!
#20
0!
#30
1!
#40
0!
#50
b1 %
b1 &
1!
0"
#60
0!
#70
b10 &
b10 %
1!
#80
0!
#90
1$
b11 %
b11 &
1!
#100
0!
#110
1#
b100 &
b100 %
1!
#120
0!
#130
b101 %
0#
b0 &
1!
#140
0!
#150
b1 &
0$
b0 %
1!
#160
0!
#170
b1 %
b10 &
1!
#180
0!
#190
b11 &
b10 %
1!
#200
0!
#210
1$
b11 %
1#
b100 &
1!
#220
0!
#230
0#
b0 &
b100 %
1!
#240
0!
#250
b101 %
b1 &
1!
#260
0!
#270
b10 &
0$
b0 %
1!
#280
0!
#290
b1 %
b11 &
1!
#300
0!
#310
1#
b100 &
b10 %
1!
#320
0!
#330
1$
b11 %
0#
b0 &
1!
#340
0!
#350
b1 &
b100 %
1!
#360
0!
#370
b101 %
b10 &
1!
#380
0!
#390
b11 &
0$
b0 %
1!
#400
0!
#410
b1 %
1#
b100 &
1!
#420
0!
#430
0#
b0 &
b10 %
1!
#440
0!
#450
1$
b11 %
b1 &
1!
#460
0!
#470
b10 &
b100 %
1!
#480
0!
#490
b101 %
b11 &
1!
#500
0!
#510
1#
b100 &
0$
b0 %
1!
#520
0!
#530
b1 %
0#
b0 &
1!
#540
0!
#550
b1 &
b10 %
1!
#560
0!
#570
1$
b11 %
b10 &
1!
#580
0!
#590
b11 &
b100 %
1!
#600
0!
#610
b101 %
1#
b100 &
1!
#620
0!
#630
0#
b0 &
0$
b0 %
1!
#640
0!
#650
b1 %
b1 &
1!
#660
0!
#670
b10 &
b10 %
1!
#680
0!
#690
1$
b11 %
b11 &
1!
#700
0!
#710
1#
b100 &
b100 %
1!
#720
0!
#730
b101 %
0#
b0 &
1!
#740
0!
#750
b1 &
0$
b0 %
1!
#760
0!
#770
b1 %
b10 &
1!
#780
0!
#790
b11 &
b10 %
1!
#800
0!
#810
1$
b11 %
1#
b100 &
1!
#820
0!
#830
0#
b0 &
b100 %
1!
#840
0!
#850
b101 %
b1 &
1!
#860
0!
#870
b10 &
0$
b0 %
1!
#880
0!
#890
b1 %
b11 &
1!
#900
0!
#910
1#
b100 &
b10 %
1!
#920
0!
#930
1$
b11 %
0#
b0 &
1!
#940
0!
#950
b1 &
b100 %
1!
#960
0!
#970
b101 %
b10 &
1!
#980
0!
#990
b11 &
0$
b0 %
1!
#1000
0!
#1010
b1 %
1#
b100 &
1!
#1020
0!
#1030
0#
b0 &
b10 %
1!
#1040
0!
#1050
1$
b11 %
b1 &
1!
#1060
0!
#1070
b10 &
b100 %
1!
#1080
0!
#1090
b101 %
b11 &
1!
#1100
0!
#1110
1#
b100 &
0$
b0 %
1!
#1120
0!
#1130
b1 %
0#
b0 &
1!
#1140
0!
#1150
b1 &
b10 %
1!
#1160
0!
#1170
1$
b11 %
b10 &
1!
#1180
0!
#1190
b11 &
b100 %
1!
#1200
0!
#1210
b101 %
1#
b100 &
1!
#1220
0!
#1230
0#
b0 &
0$
b0 %
1!
#1240
0!
#1250
b1 %
b1 &
1!
#1260
0!
#1270
b10 &
b10 %
1!
#1280
0!
#1290
1$
b11 %
b11 &
1!
#1300
0!
#1310
1#
b100 &
b100 %
1!
#1320
0!
#1330
b101 %
0#
b0 &
1!
#1340
0!
#1350
b1 &
0$
b0 %
1!
